{
  "$schema": "https://json-schema.org/draft/2020-12/schema",
  "$id": "https://raw.githubusercontent.com/api-evangelist/hubspot/refs/heads/main/json-schema/blog-posts-api-schedule-request-schema.json",
  "title": "ScheduleRequest",
  "description": "Request to schedule a blog post for publication",
  "type": "object",
  "properties": {
    "id": {
      "type": "string",
      "description": "ID of the blog post to schedule",
      "example": "500123"
    },
    "publishDate": {
      "type": "string",
      "format": "date-time",
      "description": "ISO 8601 date and time to publish",
      "example": "2025-03-15T14:30:00Z"
    }
  },
  "required": [
    "id",
    "publishDate"
  ]
}